README.rst
setup.py
probfoil/__init__.py
probfoil/data.py
probfoil/language.py
probfoil/learn.py
probfoil/probfoil.py
probfoil/rule.py
probfoil/score.py
probfoil/version.py
probfoil.egg-info/PKG-INFO
probfoil.egg-info/SOURCES.txt
probfoil.egg-info/dependency_links.txt
probfoil.egg-info/entry_points.txt
probfoil.egg-info/pbr.json
probfoil.egg-info/requires.txt
probfoil.egg-info/top_level.txt